django_aws_mail/__init__.py
django_aws_mail/admin.py
django_aws_mail/apps.py
django_aws_mail/backends.py
django_aws_mail/forms.py
django_aws_mail/handlers.py
django_aws_mail/html.py
django_aws_mail/message.py
django_aws_mail/migrations/0001_initial.py
django_aws_mail/migrations/__init__.py
django_aws_mail/models.py
django_aws_mail/settings.py
django_aws_mail/signals.py
django_aws_mail/urls.py
django_aws_mail/utils.py
django_aws_mail/verifier.py
django_aws_mail/views.py
django_aws_mail-0.3.dist-info/LICENSE
django_aws_mail-0.3.dist-info/METADATA
django_aws_mail-0.3.dist-info/WHEEL
django_aws_mail-0.3.dist-info/RECORD
