Metadata-Version: 2.3
Name: django-aws-mail
Version: 0.3
Summary: AWS mail for Django using SES and SNS.
License: MIT
Keywords: amazon,mail,aws,ses,sns,django
Author: Bas van Gaalen
Author-email: bas@webtweakers.com
Requires-Python: >=3.9
Classifier: License :: OSI Approved :: MIT License
Classifier: Programming Language :: Python :: 3
Classifier: Programming Language :: Python :: 3.9
Classifier: Programming Language :: Python :: 3.10
Classifier: Programming Language :: Python :: 3.11
Classifier: Programming Language :: Python :: 3.12
Classifier: Programming Language :: Python :: 3.13
Requires-Dist: boto3 (>=1.0.0)
Requires-Dist: cryptography (>=43.0.3)
Requires-Dist: django (>=4.2.16)
Requires-Dist: django-json-widget (>=2.0.0)
Requires-Dist: requests (>=2.32.1)
Project-URL: Repository, https://github.com/django-aws-mail/django-aws-mail
